pyriodic/__init__.py
pyriodic/interface.py
pyriodic/jobs.py
pyriodic/parse.py
pyriodic/scheduler.py
pyriodic-0.0.5.dist-info/DESCRIPTION.rst
pyriodic-0.0.5.dist-info/METADATA
pyriodic-0.0.5.dist-info/RECORD
pyriodic-0.0.5.dist-info/WHEEL
pyriodic-0.0.5.dist-info/metadata.json
pyriodic-0.0.5.dist-info/top_level.txt
