Metadata-Version: 2.0
Name: pyriodic
Version: 0.0.5
Summary: A job scheduler written in Python to run periodic tasks.
Home-page: http://ayehavgunne.github.io/pyriodic/
Author: Anthony Post
Author-email: postanthony3000@gmail.com
License: Copyright (c) 2014, Anthony Nelson Post <postanthony3000@gmail.com>
